{
	"pages": [
		{
			"page_number": 13,
			"bbox": {
				"x0": 0.0,
				"y0": 0.0,
				"x1": 552.76,
				"y1": 496.06
			},
			"blocks": [
				{
					"bbox": {
						"x0": 74.3,
						"y0": 41.56,
						"x1": 82.87,
						"y1": 51.53
					},
					"id": 0,
					"text": "4x",
					"font_name": "CeraPro-Light",
					"font_size": 8.0,
					"__tag__": "Text"
				},
				{
					"bbox": {
						"x0": 123.52,
						"y0": 41.56,
						"x1": 132.1,
						"y1": 51.53
					},
					"id": 1,
					"text": "4x",
					"font_name": "CeraPro-Light",
					"font_size": 8.0,
					"__tag__": "Text"
				},
				{
					"bbox": {
						"x0": 34.02,
						"y0": 64.51,
						"x1": 60.2,
						"y1": 96.9
					},
					"id": 2,
					"text": "10",
					"font_name": "CeraPro-Light",
					"font_size": 26.0,
					"__tag__": "Text"
				},
				{
					"bbox": {
						"x0": 454.77,
						"y0": 351.67,
						"x1": 472.24,
						"y1": 371.6
					},
					"id": 3,
					"text": "2x",
					"font_name": "CeraPro-Light",
					"font_size": 16.0,
					"__tag__": "Text"
				},
				{
					"bbox": {
						"x0": 454.77,
						"y0": 351.67,
						"x1": 472.24,
						"y1": 371.6
					},
					"id": 4,
					"text": "2x",
					"font_name": "CeraPro-Light",
					"font_size": 16.0,
					"__tag__": "Text"
				},
				{
					"bbox": {
						"x0": 328.16,
						"y0": 105.93,
						"x1": 345.64,
						"y1": 125.86
					},
					"id": 5,
					"text": "2x",
					"font_name": "CeraPro-Light",
					"font_size": 16.0,
					"__tag__": "Text"
				},
				{
					"bbox": {
						"x0": 328.16,
						"y0": 105.93,
						"x1": 345.64,
						"y1": 125.86
					},
					"id": 6,
					"text": "2x",
					"font_name": "CeraPro-Light",
					"font_size": 16.0,
					"__tag__": "Text"
				},
				{
					"bbox": {
						"x0": 529.7,
						"y0": 471.89,
						"x1": 538.59,
						"y1": 484.35
					},
					"id": 7,
					"text": "13",
					"font_name": "CeraPro-Light",
					"font_size": 10.0,
					"__tag__": "Text"
				},
				{
					"bbox": {
						"x0": 194.17,
						"y0": 222.24,
						"x1": 323.28,
						"y1": 314.64
					},
					"id": 8,
					"image_id": "image_0",
					"__tag__": "Image"
				},
				{
					"bbox": {
						"x0": 73.82,
						"y0": 28.42,
						"x1": 95.65,
						"y1": 42.56
					},
					"id": 9,
					"image_id": "image_1",
					"__tag__": "Image"
				},
				{
					"bbox": {
						"x0": 123.05,
						"y0": 26.02,
						"x1": 147.28,
						"y1": 42.57
					},
					"id": 10,
					"image_id": "image_3",
					"__tag__": "Image"
				},
				{
					"bbox": {
						"x0": 215.43,
						"y0": 229.4,
						"x1": 398.47,
						"y1": 348.92
					},
					"id": 11,
					"image_id": "image_6",
					"__tag__": "Image"
				},
				{
					"bbox": {
						"x0": 215.49,
						"y0": 229.44,
						"x1": 323.05,
						"y1": 314.4
					},
					"id": 12,
					"image_id": "image_7",
					"__tag__": "Image"
				},
				{
					"bbox": {
						"x0": 354.38,
						"y0": 317.24,
						"x1": 398.47,
						"y1": 348.92
					},
					"id": 13,
					"image_id": "image_8",
					"__tag__": "Image"
				},
				{
					"bbox": {
						"x0": 363.66,
						"y0": 326.63,
						"x1": 449.58,
						"y1": 368.14
					},
					"id": 14,
					"image_id": "image_9",
					"__tag__": "Image"
				},
				{
					"bbox": {
						"x0": 241.52,
						"y0": 130.83,
						"x1": 293.19,
						"y1": 222.99
					},
					"id": 15,
					"image_id": "image_11",
					"__tag__": "Image"
				},
				{
					"bbox": {
						"x0": 241.84,
						"y0": 222.48,
						"x1": 292.86,
						"y1": 229.92
					},
					"id": 16,
					"image_id": "image_12",
					"__tag__": "Image"
				},
				{
					"bbox": {
						"x0": 241.84,
						"y0": 229.44,
						"x1": 292.86,
						"y1": 275.28
					},
					"id": 17,
					"image_id": "image_13",
					"__tag__": "Image"
				},
				{
					"bbox": {
						"x0": 241.52,
						"y0": 129.87,
						"x1": 293.19,
						"y1": 131.79
					},
					"id": 18,
					"image_id": "image_14",
					"__tag__": "Image"
				},
				{
					"bbox": {
						"x0": 227.8,
						"y0": 80.89,
						"x1": 323.56,
						"y1": 122.4
					},
					"id": 19,
					"image_id": "image_15",
					"__tag__": "Image"
				},
				{
					"bbox": {
						"x0": 0.0,
						"y0": 0.0,
						"x1": 552.76,
						"y1": 496.06
					},
					"id": 20,
					"image_id": null,
					"__tag__": "Drawing"
				},
				{
					"bbox": {
						"x0": 34.52,
						"y0": 14.67,
						"x1": 186.59,
						"y1": 61.91
					},
					"id": 21,
					"image_id": null,
					"__tag__": "Drawing"
				},
				{
					"bbox": {
						"x0": 34.52,
						"y0": 14.67,
						"x1": 186.59,
						"y1": 61.91
					},
					"id": 22,
					"image_id": null,
					"__tag__": "Drawing"
				},
				{
					"bbox": {
						"x0": 74.49,
						"y0": 44.28,
						"x1": 78.37,
						"y1": 49.56
					},
					"id": 23,
					"image_id": null,
					"__tag__": "Drawing"
				},
				{
					"bbox": {
						"x0": 79.24,
						"y0": 45.69,
						"x1": 82.67,
						"y1": 49.56
					},
					"id": 24,
					"image_id": null,
					"__tag__": "Drawing"
				},
				{
					"bbox": {
						"x0": 123.72,
						"y0": 44.28,
						"x1": 127.6,
						"y1": 49.56
					},
					"id": 25,
					"image_id": null,
					"__tag__": "Drawing"
				},
				{
					"bbox": {
						"x0": 128.47,
						"y0": 45.69,
						"x1": 131.89,
						"y1": 49.56
					},
					"id": 26,
					"image_id": null,
					"__tag__": "Drawing"
				},
				{
					"bbox": {
						"x0": 34.95,
						"y0": 73.35,
						"x1": 40.59,
						"y1": 90.51
					},
					"id": 27,
					"image_id": null,
					"__tag__": "Drawing"
				},
				{
					"bbox": {
						"x0": 46.26,
						"y0": 73.09,
						"x1": 58.33,
						"y1": 90.77
					},
					"id": 28,
					"image_id": null,
					"__tag__": "Drawing"
				},
				{
					"bbox": {
						"x0": 355.63,
						"y0": 318.6,
						"x1": 480.74,
						"y1": 376.17
					},
					"id": 29,
					"image_id": null,
					"__tag__": "Drawing"
				},
				{
					"bbox": {
						"x0": 354.88,
						"y0": 317.85,
						"x1": 481.49,
						"y1": 376.92
					},
					"id": 30,
					"image_id": null,
					"__tag__": "Drawing"
				},
				{
					"bbox": {
						"x0": 220.68,
						"y0": 234.62,
						"x1": 396.91,
						"y1": 347.39
					},
					"id": 31,
					"image_id": null,
					"__tag__": "Drawing"
				},
				{
					"bbox": {
						"x0": 216.63,
						"y0": 298.35,
						"x1": 225.73,
						"y1": 310.85
					},
					"id": 32,
					"image_id": null,
					"__tag__": "Drawing"
				},
				{
					"bbox": {
						"x0": 311.17,
						"y0": 230.57,
						"x1": 323.67,
						"y1": 239.68
					},
					"id": 33,
					"image_id": null,
					"__tag__": "Drawing"
				},
				{
					"bbox": {
						"x0": 355.63,
						"y0": 318.6,
						"x1": 480.74,
						"y1": 376.17
					},
					"id": 34,
					"image_id": null,
					"__tag__": "Drawing"
				},
				{
					"bbox": {
						"x0": 455.44,
						"y0": 356.84,
						"x1": 472.02,
						"y1": 367.77
					},
					"id": 35,
					"image_id": null,
					"__tag__": "Drawing"
				},
				{
					"bbox": {
						"x0": 455.54,
						"y0": 356.95,
						"x1": 471.82,
						"y1": 367.67
					},
					"id": 36,
					"image_id": null,
					"__tag__": "Drawing"
				},
				{
					"bbox": {
						"x0": 455.54,
						"y0": 356.95,
						"x1": 471.82,
						"y1": 367.67
					},
					"id": 37,
					"image_id": null,
					"__tag__": "Drawing"
				},
				{
					"bbox": {
						"x0": 219.78,
						"y0": 72.86,
						"x1": 354.13,
						"y1": 130.43
					},
					"id": 38,
					"image_id": null,
					"__tag__": "Drawing"
				},
				{
					"bbox": {
						"x0": 219.03,
						"y0": 72.11,
						"x1": 354.88,
						"y1": 131.18
					},
					"id": 39,
					"image_id": null,
					"__tag__": "Drawing"
				},
				{
					"bbox": {
						"x0": 247.17,
						"y0": 91.56,
						"x1": 287.57,
						"y1": 262.8
					},
					"id": 40,
					"image_id": null,
					"__tag__": "Drawing"
				},
				{
					"bbox": {
						"x0": 243.12,
						"y0": 261.6,
						"x1": 252.22,
						"y1": 274.11
					},
					"id": 41,
					"image_id": null,
					"__tag__": "Drawing"
				},
				{
					"bbox": {
						"x0": 282.52,
						"y0": 209.87,
						"x1": 291.62,
						"y1": 222.38
					},
					"id": 42,
					"image_id": null,
					"__tag__": "Drawing"
				},
				{
					"bbox": {
						"x0": 219.78,
						"y0": 72.86,
						"x1": 354.13,
						"y1": 130.43
					},
					"id": 43,
					"image_id": null,
					"__tag__": "Drawing"
				},
				{
					"bbox": {
						"x0": 328.83,
						"y0": 111.1,
						"x1": 345.42,
						"y1": 122.03
					},
					"id": 44,
					"image_id": null,
					"__tag__": "Drawing"
				},
				{
					"bbox": {
						"x0": 328.93,
						"y0": 111.21,
						"x1": 345.22,
						"y1": 121.93
					},
					"id": 45,
					"image_id": null,
					"__tag__": "Drawing"
				},
				{
					"bbox": {
						"x0": 328.93,
						"y0": 111.21,
						"x1": 345.22,
						"y1": 121.93
					},
					"id": 46,
					"image_id": null,
					"__tag__": "Drawing"
				},
				{
					"bbox": {
						"x0": -517.74,
						"y0": 474.1,
						"x1": 517.74,
						"y1": 482.59
					},
					"id": 47,
					"image_id": null,
					"__tag__": "Drawing"
				},
				{
					"bbox": {
						"x0": 530.06,
						"y0": 475.29,
						"x1": 532.23,
						"y1": 481.89
					},
					"id": 48,
					"image_id": null,
					"__tag__": "Drawing"
				},
				{
					"bbox": {
						"x0": 533.58,
						"y0": 475.29,
						"x1": 538.02,
						"y1": 481.99
					},
					"id": 49,
					"image_id": null,
					"__tag__": "Drawing"
				}
			]
		}
	]
}