{
    "page_number": 12,
    "blocks": [
        {
            "bbox": {
                "x0": 37.19279861450195,
                "y0": 277.8145751953125,
                "x1": 46.07279968261719,
                "y1": 287.7825622558594
            },
            "id": 0,
            "text": "2x",
            "font_name": "CeraPro-Light",
            "font_size": 8.0,
            "__tag__": "Text"
        },
        {
            "bbox": {
                "x0": 79.78849792480469,
                "y0": 277.8145751953125,
                "x1": 88.66850280761719,
                "y1": 287.7825622558594
            },
            "id": 1,
            "text": "2x",
            "font_name": "CeraPro-Light",
            "font_size": 8.0,
            "__tag__": "Text"
        },
        {
            "bbox": {
                "x0": 124.78410339355469,
                "y0": 277.8145751953125,
                "x1": 131.99209594726562,
                "y1": 287.7825622558594
            },
            "id": 2,
            "text": "1x",
            "font_name": "CeraPro-Light",
            "font_size": 8.0,
            "__tag__": "Text"
        },
        {
            "bbox": {
                "x0": 14.173199653625488,
                "y0": 298.36517333984375,
                "x1": 29.04520034790039,
                "y1": 330.76116943359375
            },
            "id": 3,
            "text": "8",
            "font_name": "CeraPro-Light",
            "font_size": 26.0,
            "__tag__": "Text"
        },
        {
            "bbox": {
                "x0": 344.565185546875,
                "y0": 43.957183837890625,
                "x1": 351.7731628417969,
                "y1": 53.9251823425293
            },
            "id": 4,
            "text": "1x",
            "font_name": "CeraPro-Light",
            "font_size": 8.0,
            "__tag__": "Text"
        },
        {
            "bbox": {
                "x0": 301.6094970703125,
                "y0": 43.957183837890625,
                "x1": 308.8174743652344,
                "y1": 53.9251823425293
            },
            "id": 5,
            "text": "1x",
            "font_name": "CeraPro-Light",
            "font_size": 8.0,
            "__tag__": "Text"
        },
        {
            "bbox": {
                "x0": 393.2807922363281,
                "y0": 43.957183837890625,
                "x1": 400.48876953125,
                "y1": 53.9251823425293
            },
            "id": 6,
            "text": "1x",
            "font_name": "CeraPro-Light",
            "font_size": 8.0,
            "__tag__": "Text"
        },
        {
            "bbox": {
                "x0": 280.6299133300781,
                "y0": 64.50787353515625,
                "x1": 294.825927734375,
                "y1": 96.90387725830078
            },
            "id": 7,
            "text": "9",
            "font_name": "CeraPro-Light",
            "font_size": 26.0,
            "__tag__": "Text"
        },
        {
            "bbox": {
                "x0": 46.229000091552734,
                "y0": 43.237274169921875,
                "x1": 53.4370002746582,
                "y1": 53.20527267456055
            },
            "id": 8,
            "text": "1x",
            "font_name": "CeraPro-Light",
            "font_size": 8.0,
            "__tag__": "Text"
        },
        {
            "bbox": {
                "x0": 14.173199653625488,
                "y0": 64.50787353515625,
                "x1": 26.91320037841797,
                "y1": 96.90387725830078
            },
            "id": 9,
            "text": "7",
            "font_name": "CeraPro-Light",
            "font_size": 26.0,
            "__tag__": "Text"
        },
        {
            "bbox": {
                "x0": 106.14790344238281,
                "y0": 43.237274169921875,
                "x1": 113.35589599609375,
                "y1": 53.20527267456055
            },
            "id": 10,
            "text": "1x",
            "font_name": "CeraPro-Light",
            "font_size": 8.0,
            "__tag__": "Text"
        },
        {
            "bbox": {
                "x0": 14.173199653625488,
                "y0": 471.8898010253906,
                "x1": 23.24319839477539,
                "y1": 484.34979248046875
            },
            "id": 11,
            "text": "12",
            "font_name": "CeraPro-Light",
            "font_size": 10.0,
            "__tag__": "Text"
        },
        {
            "bbox": {
                "x0": 68.67021179199219,
                "y0": 340.78253173828125,
                "x1": 197.78689575195312,
                "y1": 430.53753662109375
            },
            "id": 12,
            "image_id": "image_0",
            "__tag__": "Image"
        },
        {
            "bbox": {
                "x0": 68.54920959472656,
                "y0": 107.23929595947266,
                "x1": 197.9076690673828,
                "y1": 191.7139892578125
            },
            "id": 13,
            "image_id": "image_1",
            "__tag__": "Image"
        },
        {
            "bbox": {
                "x0": 36.718231201171875,
                "y0": 260.3570861816406,
                "x1": 58.54736328125,
                "y1": 278.82415771484375
            },
            "id": 14,
            "image_id": "image_2",
            "__tag__": "Image"
        },
        {
            "bbox": {
                "x0": 79.31334686279297,
                "y0": 257.4761962890625,
                "x1": 103.54360961914062,
                "y1": 278.8250732421875
            },
            "id": 15,
            "image_id": "image_4",
            "__tag__": "Image"
        },
        {
            "bbox": {
                "x0": 124.30998229980469,
                "y0": 263.9666442871094,
                "x1": 144.6983184814453,
                "y1": 278.8146667480469
            },
            "id": 16,
            "image_id": "image_6",
            "__tag__": "Image"
        },
        {
            "bbox": {
                "x0": 335.1268005371094,
                "y0": 224.8856658935547,
                "x1": 464.24346923828125,
                "y1": 314.64068603515625
            },
            "id": 17,
            "image_id": "image_8",
            "__tag__": "Image"
        },
        {
            "bbox": {
                "x0": 344.0890808105469,
                "y0": 26.97991371154785,
                "x1": 374.0812683105469,
                "y1": 44.96661376953125
            },
            "id": 18,
            "image_id": "image_9",
            "__tag__": "Image"
        },
        {
            "bbox": {
                "x0": 301.1343688964844,
                "y0": 23.618831634521484,
                "x1": 325.3646240234375,
                "y1": 44.96771240234375
            },
            "id": 19,
            "image_id": "image_11",
            "__tag__": "Image"
        },
        {
            "bbox": {
                "x0": 392.8066711425781,
                "y0": 30.10918426513672,
                "x1": 413.19500732421875,
                "y1": 44.95721435546875
            },
            "id": 20,
            "image_id": "image_13",
            "__tag__": "Image"
        },
        {
            "bbox": {
                "x0": 45.75614929199219,
                "y0": 24.339214324951172,
                "x1": 78.38188934326172,
                "y1": 44.24725341796875
            },
            "id": 21,
            "image_id": "image_15",
            "__tag__": "Image"
        },
        {
            "bbox": {
                "x0": 105.67182159423828,
                "y0": 26.259912490844727,
                "x1": 135.6640167236328,
                "y1": 44.246612548828125
            },
            "id": 22,
            "image_id": "image_18",
            "__tag__": "Image"
        },
        {
            "bbox": {
                "x0": 0.0,
                "y0": 9.1552734375e-05,
                "x1": 552.7556762695312,
                "y1": 496.06298828125
            },
            "id": 23,
            "image_id": null,
            "__tag__": "Drawing"
        },
        {
            "bbox": {
                "x0": 266.45660400390625,
                "y0": 14.17327880859375,
                "x1": 266.45660400390625,
                "y1": 481.8902893066406
            },
            "id": 24,
            "image_id": null,
            "__tag__": "Drawing"
        },
        {
            "bbox": {
                "x0": 14.672869682312012,
                "y0": 248.5310821533203,
                "x1": 166.7440643310547,
                "y1": 295.7709655761719
            },
            "id": 25,
            "image_id": null,
            "__tag__": "Drawing"
        },
        {
            "bbox": {
                "x0": 14.67300033569336,
                "y0": 248.53097534179688,
                "x1": 166.74400329589844,
                "y1": 295.77099609375
            },
            "id": 26,
            "image_id": null,
            "__tag__": "Drawing"
        },
        {
            "bbox": {
                "x0": 37.57680130004883,
                "y0": 280.45458984375,
                "x1": 41.152801513671875,
                "y1": 285.8145751953125
            },
            "id": 27,
            "image_id": null,
            "__tag__": "Drawing"
        },
        {
            "bbox": {
                "x0": 42.44076919555664,
                "y0": 281.9505920410156,
                "x1": 45.86476135253906,
                "y1": 285.8145751953125
            },
            "id": 28,
            "image_id": null,
            "__tag__": "Drawing"
        },
        {
            "bbox": {
                "x0": 80.17250061035156,
                "y0": 280.45458984375,
                "x1": 83.74849700927734,
                "y1": 285.8145751953125
            },
            "id": 29,
            "image_id": null,
            "__tag__": "Drawing"
        },
        {
            "bbox": {
                "x0": 85.03646850585938,
                "y0": 281.9505920410156,
                "x1": 88.46047973632812,
                "y1": 285.8145751953125
            },
            "id": 30,
            "image_id": null,
            "__tag__": "Drawing"
        },
        {
            "bbox": {
                "x0": 125.07211303710938,
                "y0": 280.53460693359375,
                "x1": 126.80811309814453,
                "y1": 285.8145751953125
            },
            "id": 31,
            "image_id": null,
            "__tag__": "Drawing"
        },
        {
            "bbox": {
                "x0": 128.3600616455078,
                "y0": 281.9505920410156,
                "x1": 131.78407287597656,
                "y1": 285.8145751953125
            },
            "id": 32,
            "image_id": null,
            "__tag__": "Drawing"
        },
        {
            "bbox": {
                "x0": 15.759200096130371,
                "y0": 306.9451904296875,
                "x1": 27.459199905395508,
                "y1": 324.62518310546875
            },
            "id": 33,
            "image_id": null,
            "__tag__": "Drawing"
        },
        {
            "bbox": {
                "x0": 281.1300048828125,
                "y0": 14.673126220703125,
                "x1": 433.2009582519531,
                "y1": 61.91302490234375
            },
            "id": 34,
            "image_id": null,
            "__tag__": "Drawing"
        },
        {
            "bbox": {
                "x0": 280.6300354003906,
                "y0": 14.173126220703125,
                "x1": 433.7009582519531,
                "y1": 62.41302490234375
            },
            "id": 35,
            "image_id": null,
            "__tag__": "Drawing"
        },
        {
            "bbox": {
                "x0": 344.8531799316406,
                "y0": 46.67718505859375,
                "x1": 346.58917236328125,
                "y1": 51.957183837890625
            },
            "id": 36,
            "image_id": null,
            "__tag__": "Drawing"
        },
        {
            "bbox": {
                "x0": 348.1411437988281,
                "y0": 48.093170166015625,
                "x1": 351.56512451171875,
                "y1": 51.957183837890625
            },
            "id": 37,
            "image_id": null,
            "__tag__": "Drawing"
        },
        {
            "bbox": {
                "x0": 301.8974914550781,
                "y0": 46.67718505859375,
                "x1": 303.63348388671875,
                "y1": 51.957183837890625
            },
            "id": 38,
            "image_id": null,
            "__tag__": "Drawing"
        },
        {
            "bbox": {
                "x0": 305.1854553222656,
                "y0": 48.093170166015625,
                "x1": 308.60943603515625,
                "y1": 51.957183837890625
            },
            "id": 39,
            "image_id": null,
            "__tag__": "Drawing"
        },
        {
            "bbox": {
                "x0": 393.56878662109375,
                "y0": 46.67718505859375,
                "x1": 395.3047790527344,
                "y1": 51.957183837890625
            },
            "id": 40,
            "image_id": null,
            "__tag__": "Drawing"
        },
        {
            "bbox": {
                "x0": 396.85675048828125,
                "y0": 48.093170166015625,
                "x1": 400.2807312011719,
                "y1": 51.957183837890625
            },
            "id": 41,
            "image_id": null,
            "__tag__": "Drawing"
        },
        {
            "bbox": {
                "x0": 282.0859069824219,
                "y0": 73.08786010742188,
                "x1": 293.3699035644531,
                "y1": 90.50787353515625
            },
            "id": 42,
            "image_id": null,
            "__tag__": "Drawing"
        },
        {
            "bbox": {
                "x0": 14.672869682312012,
                "y0": 14.673126220703125,
                "x1": 166.7440643310547,
                "y1": 61.91302490234375
            },
            "id": 43,
            "image_id": null,
            "__tag__": "Drawing"
        },
        {
            "bbox": {
                "x0": 14.67300033569336,
                "y0": 14.673004150390625,
                "x1": 166.74400329589844,
                "y1": 61.912994384765625
            },
            "id": 44,
            "image_id": null,
            "__tag__": "Drawing"
        },
        {
            "bbox": {
                "x0": 46.516998291015625,
                "y0": 45.957275390625,
                "x1": 48.25300979614258,
                "y1": 51.237274169921875
            },
            "id": 45,
            "image_id": null,
            "__tag__": "Drawing"
        },
        {
            "bbox": {
                "x0": 49.80495834350586,
                "y0": 47.373260498046875,
                "x1": 53.22895812988281,
                "y1": 51.237274169921875
            },
            "id": 46,
            "image_id": null,
            "__tag__": "Drawing"
        },
        {
            "bbox": {
                "x0": 15.031200408935547,
                "y0": 73.34786987304688,
                "x1": 26.237199783325195,
                "y1": 90.50787353515625
            },
            "id": 47,
            "image_id": null,
            "__tag__": "Drawing"
        },
        {
            "bbox": {
                "x0": 106.4359130859375,
                "y0": 45.957275390625,
                "x1": 108.17191314697266,
                "y1": 51.237274169921875
            },
            "id": 48,
            "image_id": null,
            "__tag__": "Drawing"
        },
        {
            "bbox": {
                "x0": 109.72386169433594,
                "y0": 47.373260498046875,
                "x1": 113.14787292480469,
                "y1": 51.237274169921875
            },
            "id": 49,
            "image_id": null,
            "__tag__": "Drawing"
        },
        {
            "bbox": {
                "x0": 35.015750885009766,
                "y0": 474.10235595703125,
                "x1": 1070.49560546875,
                "y1": 482.5902099609375
            },
            "id": 50,
            "image_id": null,
            "__tag__": "Drawing"
        },
        {
            "bbox": {
                "x0": 34.0157585144043,
                "y0": 473.10235595703125,
                "x1": 1071.495361328125,
                "y1": 483.5902099609375
            },
            "id": 51,
            "image_id": null,
            "__tag__": "Drawing"
        },
        {
            "bbox": {
                "x0": 35.015750885009766,
                "y0": 474.10235595703125,
                "x1": 47.39170837402344,
                "y1": 482.5904846191406
            },
            "id": 52,
            "image_id": null,
            "__tag__": "Drawing"
        },
        {
            "bbox": {
                "x0": 34.0157585144043,
                "y0": 473.10235595703125,
                "x1": 48.39168930053711,
                "y1": 483.5904541015625
            },
            "id": 53,
            "image_id": null,
            "__tag__": "Drawing"
        },
        {
            "bbox": {
                "x0": 41.5543212890625,
                "y0": 471.3116149902344,
                "x1": 55.228271484375,
                "y1": 484.9844970703125
            },
            "id": 54,
            "image_id": null,
            "__tag__": "Drawing"
        },
        {
            "bbox": {
                "x0": 43.41539001464844,
                "y0": 471.0616149902344,
                "x1": 53.36751174926758,
                "y1": 485.2344970703125
            },
            "id": 55,
            "image_id": null,
            "__tag__": "Drawing"
        },
        {
            "bbox": {
                "x0": 54.29964065551758,
                "y0": 475.10235595703125,
                "x1": 55.47800064086914,
                "y1": 481.5902404785156
            },
            "id": 56,
            "image_id": null,
            "__tag__": "Drawing"
        },
        {
            "bbox": {
                "x0": 52.52988052368164,
                "y0": 473.10235595703125,
                "x1": 54.7919807434082,
                "y1": 483.5902099609375
            },
            "id": 57,
            "image_id": null,
            "__tag__": "Drawing"
        },
        {
            "bbox": {
                "x0": 41.305110931396484,
                "y0": 475.10235595703125,
                "x1": 42.48316955566406,
                "y1": 481.5904846191406
            },
            "id": 58,
            "image_id": null,
            "__tag__": "Drawing"
        },
        {
            "bbox": {
                "x0": 41.9911003112793,
                "y0": 473.10235595703125,
                "x1": 44.25321960449219,
                "y1": 483.5904541015625
            },
            "id": 59,
            "image_id": null,
            "__tag__": "Drawing"
        },
        {
            "bbox": {
                "x0": 41.5543212890625,
                "y0": 471.3116149902344,
                "x1": 55.228271484375,
                "y1": 484.9844970703125
            },
            "id": 60,
            "image_id": null,
            "__tag__": "Drawing"
        },
        {
            "bbox": {
                "x0": 44.12644958496094,
                "y0": 473.8829345703125,
                "x1": 52.65639877319336,
                "y1": 482.41290283203125
            },
            "id": 61,
            "image_id": null,
            "__tag__": "Drawing"
        },
        {
            "bbox": {
                "x0": 43.87644958496094,
                "y0": 473.6329345703125,
                "x1": 52.90639877319336,
                "y1": 482.66290283203125
            },
            "id": 62,
            "image_id": null,
            "__tag__": "Drawing"
        },
        {
            "bbox": {
                "x0": 44.12644958496094,
                "y0": 473.8829345703125,
                "x1": 52.65639877319336,
                "y1": 482.41290283203125
            },
            "id": 63,
            "image_id": null,
            "__tag__": "Drawing"
        },
        {
            "bbox": {
                "x0": 14.532609939575195,
                "y0": 475.2897644042969,
                "x1": 16.70261001586914,
                "y1": 481.8898010253906
            },
            "id": 64,
            "image_id": null,
            "__tag__": "Drawing"
        },
        {
            "bbox": {
                "x0": 18.232559204101562,
                "y0": 475.1897888183594,
                "x1": 22.702560424804688,
                "y1": 481.8898010253906
            },
            "id": 65,
            "image_id": null,
            "__tag__": "Drawing"
        }
    ],
    "bbox": {
        "x0": 0.0,
        "y0": 0.0,
        "x1": 552.7559814453125,
        "y1": 496.06298828125
    }
}